{"bipashabasu": "DSuHsc0jS2p", "sonamkapoor": "DSoqxPKigAT", "taapsee": "DSxLju7iDjA", "parineetichopra": "DS4f7GKjB01", "deepikapadukone": "DSM6J0JkpPH", "aliaabhatt": "DSzAXwEDGIM", "katrinakaif": "DSsctfPjcVs", "shraddhakapoor": "DSNS8taiM6U", "kiaraaliaadvani": "DSmHRRMjmlN", "dishapatani": "DSb2KzLDYyx", "kritisanon": "DS5BqjtjWbZ", "jacquelinef143": "DQHC5BAk8Nr", "norafatehi": "DShbPqrjEfk", "janhvikapoor": "DSpewMFiKmH", "saraalikhan95": "DStwz6qDK6I", "rakulpreet": "DS4Fnu1Er4T", "ananyapanday": "DSZTFE4DXFI", "tarasutaria": "DS17tWdjMJF", "hegdepooja": "DSzjXmfk6Vb", "rashmika_mandanna": "DS2xZ_wE8Xx"}